{"5AA": "", "5AD": "", "5AE": "", "5AF": "woking", "5AG": "woking", "5AH": "woking", "5AJ": "woking", "5AL": "woking", "5AN": "woking", "5AP": "woking", "5AQ": "woking", "5AR": "woking", "5AS": "woking", "5AT": "woking", "5AU": "woking", "6AA": "surrey-heath", "6AB": "surrey-heath", "6AD": "surrey-heath", "6AE": "surrey-heath", "6AF": "surrey-heath", "6AG": "surrey-heath", "6AH": "surrey-heath", "6AJ": "surrey-heath", "6AL": "surrey-heath", "6AN": "surrey-heath", "6AP": "surrey-heath", "6AQ": "surrey-heath", "6AR": "surrey-heath", "6AS": "surrey-heath", "6AT": "surrey-heath", "6AU": "surrey-heath", "6AW": "surrey-heath", "6AX": "surrey-heath", "6AY": "surrey-heath", "6AZ": "surrey-heath", "6BA": "surrey-heath", "6BB": "surrey-heath", "6BH": "surrey-heath", "6BJ": "surrey-heath", "6BL": "surrey-heath", "6BN": "surrey-heath", "6BP": "surrey-heath", "6BS": "surrey-heath", "6BT": "surrey-heath", "6BU": "surrey-heath", "6BW": "surrey-heath", "6BX": "surrey-heath", "6BY": "surrey-heath", "6BZ": "surrey-heath", "6DA": "surrey-heath", "6DB": "surrey-heath", "6DD": "surrey-heath", "6DE": "surrey-heath", "6DF": "surrey-heath", "6DG": "surrey-heath", "6DH": "surrey-heath", "6DJ": "surrey-heath", "6DL": "surrey-heath", "6DN": "surrey-heath", "6DP": "surrey-heath", "6DQ": "surrey-heath", "6DS": "surrey-heath", "6DT": "surrey-heath", "6DU": "surrey-heath", "6DW": "surrey-heath", "6DX": "surrey-heath", "6DY": "surrey-heath", "6DZ": "surrey-heath", "6EA": "surrey-heath", "6EB": "surrey-heath", "6ED": "surrey-heath", "6EE": "surrey-heath", "6EN": "surrey-heath", "6EP": "surrey-heath", "6ER": "surrey-heath", "6ET": "surrey-heath", "6EU": "surrey-heath", "6EW": "surrey-heath", "6EX": "surrey-heath", "6EY": "surrey-heath", "6EZ": "surrey-heath", "6HA": "surrey-heath", "6HB": "surrey-heath", "6HD": "surrey-heath", "6HE": "surrey-heath", "6HF": "surrey-heath", "6HJ": "surrey-heath", "6HL": "surrey-heath", "6HP": "surrey-heath", "6HR": "surrey-heath", "6HS": "surrey-heath", "6HT": "surrey-heath", "6HU": "surrey-heath", "6HX": "surrey-heath", "6HY": "surrey-heath", "6HZ": "surrey-heath", "6JA": "surrey-heath", "6JB": "surrey-heath", "6JD": "surrey-heath", "6JE": "surrey-heath", "6JF": "surrey-heath", "6JG": "surrey-heath", "6JH": "surrey-heath", "6JJ": "surrey-heath", "6JL": "surrey-heath", "6JN": "surrey-heath", "6JP": "surrey-heath", "6JQ": "surrey-heath", "6JR": "surrey-heath", "6JS": "surrey-heath", "6JT": "surrey-heath", "6JU": "surrey-heath", "6JW": "surrey-heath", "6JX": "surrey-heath", "6JY": "surrey-heath", "6JZ": "surrey-heath", "6LA": "surrey-heath", "6LB": "surrey-heath", "6LD": "surrey-heath", "6LE": "surrey-heath", "6LF": "surrey-heath", "6LG": "surrey-heath", "6LH": "surrey-heath", "6LJ": "surrey-heath", "6LL": "surrey-heath", "6LN": "surrey-heath", "6LP": "surrey-heath", "6LQ": "surrey-heath", "6LR": "surrey-heath", "6LS": "surrey-heath", "6LT": "surrey-heath", "6LU": "surrey-heath", "6LW": "surrey-heath", "6LX": "surrey-heath", "6LZ": "surrey-heath", "6NA": "surrey-heath", "6NB": "surrey-heath", "6ND": "surrey-heath", "6NE": "surrey-heath", "6NF": "surrey-heath", "6NG": "surrey-heath", "6NN": "surrey-heath", "6NQ": "surrey-heath", "6PA": "surrey-heath", "6PB": "surrey-heath", "6PD": "surrey-heath", "6PE": "surrey-heath", "6PF": "surrey-heath", "6PG": "surrey-heath", "6PH": "surrey-heath", "6PJ": "surrey-heath", "6PL": "surrey-heath", "6PN": "surrey-heath", "6PP": "surrey-heath", "6PQ": "windsor", "6PR": "surrey-heath", "6PS": "surrey-heath", "6PT": "surrey-heath", "6PW": "surrey-heath", "6PX": "surrey-heath", "6QA": "surrey-heath", "6QB": "surrey-heath", "6QD": "surrey-heath", "6QE": "surrey-heath", "6QF": "surrey-heath", "6QG": "surrey-heath", "6QH": "surrey-heath", "6QJ": "surrey-heath", "6QL": "surrey-heath", "6QN": "surrey-heath", "6QQ": "surrey-heath", "6UN": "surrey-heath", "6UP": "surrey-heath", "6UQ": "surrey-heath", "6UR": "surrey-heath", "6US": "surrey-heath", "6UT": "surrey-heath", "6UU": "surrey-heath", "6UW": "surrey-heath", "6UX": "surrey-heath", "6UY": "surrey-heath", "6UZ": "surrey-heath", "6WA": "surrey-heath", "6WB": "surrey-heath", "6WD": "surrey-heath", "6WE": "surrey-heath", "6WF": "surrey-heath", "6WG": "surrey-heath", "6WH": "surrey-heath", "6WL": "surrey-heath", "6WN": "surrey-heath", "6WP": "surrey-heath", "6WQ": "surrey-heath", "6WR": "surrey-heath", "6WS": "surrey-heath", "6WT": "surrey-heath", "6WU": "surrey-heath", "6WW": "surrey-heath", "6WX": "surrey-heath", "6WY": "surrey-heath", "6WZ": "surrey-heath", "6XA": "surrey-heath", "6XB": "surrey-heath", "6XD": "surrey-heath", "6XE": "surrey-heath", "6XF": "surrey-heath", "6XG": "surrey-heath", "6XH": "surrey-heath", "6XJ": "surrey-heath", "6XL": "surrey-heath", "6XN": "surrey-heath", "6XP": "surrey-heath", "6XQ": "surrey-heath", "6XR": "surrey-heath", "6XS": "surrey-heath", "6XT": "surrey-heath", "6XU": "surrey-heath", "6XW": "surrey-heath", "6XX": "surrey-heath", "6XY": "surrey-heath", "6XZ": "surrey-heath", "6YA": "surrey-heath", "6YB": "surrey-heath", "6YD": "surrey-heath", "6YE": "surrey-heath", "6YF": "surrey-heath", "6YG": "surrey-heath", "6YH": "surrey-heath", "6YJ": "surrey-heath", "6YL": "surrey-heath", "6YN": "surrey-heath", "6YP": "surrey-heath", "6YQ": "surrey-heath", "6YR": "surrey-heath", "6YS": "surrey-heath", "6YT": "surrey-heath", "6YU": "surrey-heath", "6YW": "surrey-heath", "6YX": "surrey-heath", "6YY": "surrey-heath", "6YZ": "surrey-heath", "6ZA": "surrey-heath", "6ZD": "surrey-heath", "6ZG": "surrey-heath", "6ZJ": "surrey-heath", "6ZL": "surrey-heath", "6ZN": "surrey-heath", "6ZP": "surrey-heath", "6ZQ": "surrey-heath", "6ZR": "surrey-heath", "6ZU": "surrey-heath", "6ZX": "surrey-heath"}