{"0EA": "west-lancashire", "0EB": "west-lancashire", "0ED": "west-lancashire", "0EE": "west-lancashire", "0EF": "west-lancashire", "0EG": "west-lancashire", "0EH": "west-lancashire", "0EJ": "west-lancashire", "0EL": "west-lancashire", "0EN": "west-lancashire", "0EP": "west-lancashire", "0EQ": "west-lancashire", "0ER": "west-lancashire", "0ES": "west-lancashire", "0ET": "west-lancashire", "0EU": "west-lancashire", "0EW": "west-lancashire", "0EX": "west-lancashire", "0EY": "west-lancashire", "0EZ": "west-lancashire", "0HA": "west-lancashire", "0HB": "west-lancashire", "0HD": "west-lancashire", "0HE": "west-lancashire", "0HF": "west-lancashire", "0HG": "west-lancashire", "0HH": "west-lancashire", "0HJ": "west-lancashire", "0HL": "west-lancashire", "0HN": "west-lancashire", "0HP": "west-lancashire", "0HQ": "west-lancashire", "0HR": "west-lancashire", "0HS": "west-lancashire", "0HT": "west-lancashire", "0HU": "west-lancashire", "0HW": "west-lancashire", "0HX": "west-lancashire", "0HY": "west-lancashire", "0HZ": "west-lancashire", "0JA": "west-lancashire", "0JB": "west-lancashire", "0JD": "west-lancashire", "0JE": "west-lancashire", "0JF": "west-lancashire", "0JG": "west-lancashire", "0WA": "west-lancashire", "0WX": "west-lancashire", "0WY": "west-lancashire", "0WZ": "west-lancashire", "0YW": "west-lancashire", "0YX": "west-lancashire", "1LA": "west-lancashire", "1LB": "west-lancashire", "1LD": "west-lancashire", "1LE": "west-lancashire", "1LF": "west-lancashire", "1LG": "west-lancashire", "1LH": "west-lancashire", "1LJ": "west-lancashire", "1LL": "west-lancashire", "1LN": "west-lancashire", "1LP": "west-lancashire", "1LQ": "west-lancashire", "1LR": "west-lancashire", "1LS": "west-lancashire", "1LT": "west-lancashire", "1LU": "west-lancashire", "1LW": "west-lancashire", "1LX": "west-lancashire", "1LZ": "west-lancashire", "1NA": "west-lancashire", "1NB": "west-lancashire", "1ND": "west-lancashire", "1NE": "west-lancashire", "1NF": "west-lancashire", "1NG": "west-lancashire", "1NH": "west-lancashire", "1NJ": "west-lancashire", "1NL": "west-lancashire", "1NN": "west-lancashire", "1NP": "west-lancashire", "1NQ": "west-lancashire", "1NR": "west-lancashire", "1NS": "west-lancashire", "1NT": "west-lancashire", "1NU": "west-lancashire", "1NW": "west-lancashire", "1NX": "west-lancashire", "1NY": "west-lancashire", "1NZ": "west-lancashire", "1PA": "west-lancashire", "1PB": "west-lancashire", "1PD": "west-lancashire", "1PE": "west-lancashire", "1PF": "west-lancashire", "1PG": "west-lancashire", "1PH": "west-lancashire", "1PJ": "west-lancashire", "1PL": "west-lancashire", "1PN": "west-lancashire", "1PP": "west-lancashire", "1PQ": "west-lancashire", "1PR": "west-lancashire", "1PS": "west-lancashire", "1PT": "west-lancashire", "1PU": "west-lancashire", "1PW": "west-lancashire", "1PX": "west-lancashire", "1PY": "west-lancashire", "1PZ": "west-lancashire", "1QA": "west-lancashire", "1QB": "west-lancashire", "1QD": "west-lancashire", "1QE": "west-lancashire", "1QF": "west-lancashire", "1QG": "west-lancashire", "1QH": "west-lancashire", "1QJ": "west-lancashire", "1QL": "west-lancashire", "1QN": "west-lancashire", "1QP": "west-lancashire", "1QQ": "west-lancashire", "1QR": "west-lancashire", "1QS": "west-lancashire", "1QT": "west-lancashire", "1QW": "west-lancashire", "1QX": "west-lancashire", "1RB": "west-lancashire", "1RF": "west-lancashire", "1RG": "west-lancashire", "1RH": "west-lancashire", "1RJ": "west-lancashire", "1RL": "west-lancashire", "1RN": "west-lancashire", "1RP": "west-lancashire", "1RQ": "west-lancashire", "1RR": "west-lancashire", "1RS": "west-lancashire", "1RT": "west-lancashire", "1RU": "west-lancashire", "1RW": "west-lancashire", "1RX": "west-lancashire", "1RY": "west-lancashire", "1RZ": "west-lancashire", "1SL": "west-lancashire", "1WG": "west-lancashire", "1WH": "west-lancashire", "1WJ": "west-lancashire", "1WL": "west-lancashire", "1WN": "west-lancashire", "1WP": "west-lancashire", "1WQ": "west-lancashire", "1WR": "west-lancashire", "1WS": "west-lancashire", "1WT": "west-lancashire", "1WU": "west-lancashire", "1WW": "west-lancashire", "1WX": "west-lancashire", "1WY": "west-lancashire", "1WZ": "west-lancashire", "1XA": "west-lancashire", "2AA": "west-lancashire", "2AB": "west-lancashire", "2AE": "west-lancashire", "2AF": "west-lancashire", "2AG": "west-lancashire", "2AH": "west-lancashire", "2AJ": "west-lancashire", "2AL": "west-lancashire", "2AN": "west-lancashire", "2AP": "west-lancashire", "2AQ": "west-lancashire", "2AR": "west-lancashire", "2AS": "west-lancashire", "2AT": "west-lancashire", "2AU": "west-lancashire", "2AW": "west-lancashire", "2AX": "west-lancashire", "2AY": "west-lancashire", "2AZ": "west-lancashire", "2BA": "west-lancashire", "2BB": "west-lancashire", "2BD": "west-lancashire", "2BE": "west-lancashire", "2BF": "west-lancashire", "2BG": "west-lancashire", "2BH": "west-lancashire", "2BJ": "west-lancashire", "2BL": "west-lancashire", "2BN": "west-lancashire", "2BP": "west-lancashire", "2BQ": "west-lancashire", "2BR": "west-lancashire", "2BS": "west-lancashire", "2BT": "west-lancashire", "2BU": "west-lancashire", "2BW": "west-lancashire", "2BX": "west-lancashire", "2BY": "west-lancashire", "2BZ": "west-lancashire", "2DA": "west-lancashire", "2DB": "west-lancashire", "2DD": "west-lancashire", "2DE": "west-lancashire", "2DF": "west-lancashire", "2DG": "west-lancashire", "2DH": "west-lancashire", "2DJ": "west-lancashire", "2DL": "west-lancashire", "2DN": "west-lancashire", "2DP": "west-lancashire", "2DQ": "west-lancashire", "2DR": "west-lancashire", "2DS": "west-lancashire", "2DT": "west-lancashire", "2DU": "west-lancashire", "2DW": "west-lancashire", "2DX": "west-lancashire", "2DY": "west-lancashire", "2DZ": "west-lancashire", "2EA": "west-lancashire", "2EB": "west-lancashire", "2ED": "west-lancashire", "2EE": "west-lancashire", "2EF": "west-lancashire", "2EG": "west-lancashire", "2EH": "west-lancashire", "2EJ": "west-lancashire", "2EL": "west-lancashire", "2EN": "west-lancashire", "2EP": "west-lancashire", "2EQ": "west-lancashire", "2ER": "west-lancashire", "2ES": "west-lancashire", "2ET": "west-lancashire", "2EU": "west-lancashire", "2EW": "west-lancashire", "2EX": "west-lancashire", "2EY": "west-lancashire", "2EZ": "west-lancashire", "2FA": "west-lancashire", "2FB": "west-lancashire", "2FD": "west-lancashire", "2FE": "west-lancashire", "2FF": "west-lancashire", "2FG": "west-lancashire", "2FH": "west-lancashire", "2HB": "west-lancashire", "2HD": "west-lancashire", "2HE": "west-lancashire", "2HG": "west-lancashire", "2HH": "west-lancashire", "2HJ": "west-lancashire", "2HL": "west-lancashire", "2HN": "west-lancashire", "2HP": "west-lancashire", "2HQ": "west-lancashire", "2HR": "west-lancashire", "2HU": "west-lancashire", "2HX": "west-lancashire", "2HY": "west-lancashire", "2HZ": "west-lancashire", "2JA": "west-lancashire", "2JB": "west-lancashire", "2JE": "west-lancashire", "2JF": "west-lancashire", "2JG": "west-lancashire", "2JH": "west-lancashire", "2JJ": "west-lancashire", "2JL": "west-lancashire", "2JN": "west-lancashire", "2JP": "west-lancashire", "2JQ": "west-lancashire", "2JR": "west-lancashire", "2JS": "west-lancashire", "2JT": "west-lancashire", "2JU": "west-lancashire", "2JW": "west-lancashire", "2JX": "west-lancashire", "2SA": "west-lancashire", "2SB": "west-lancashire", "2SD": "west-lancashire", "2SE": "west-lancashire", "2SF": "west-lancashire", "2SG": "west-lancashire", "2SH": "west-lancashire", "2SJ": "west-lancashire", "2SL": "west-lancashire", "2SN": "west-lancashire", "2SP": "west-lancashire", "2SQ": "west-lancashire", "2SR": "west-lancashire", "2SS": "west-lancashire", "2ST": "west-lancashire", "2SU": "west-lancashire", "2SW": "west-lancashire", "2SX": "west-lancashire", "2SY": "west-lancashire", "2SZ": "west-lancashire", "2TA": "west-lancashire", "2TB": "west-lancashire", "2TD": "west-lancashire", "2TE": "west-lancashire", "2TF": "west-lancashire", "2TH": "west-lancashire", "2WA": "west-lancashire", "2WB": "west-lancashire", "2WD": "west-lancashire", "2WE": "west-lancashire", "2WF": "west-lancashire", "2WG": "west-lancashire", "2WH": "west-lancashire", "2WQ": "west-lancashire", "2WR": "west-lancashire", "2WS": "west-lancashire", "2WT": "west-lancashire", "2WU": "west-lancashire", "2WW": "west-lancashire", "2WX": "west-lancashire", "2WY": "west-lancashire", "2WZ": "west-lancashire", "2XA": "west-lancashire", "2XB": "west-lancashire", "2XD": "west-lancashire", "2XE": "west-lancashire", "2XF": "west-lancashire", "2XG": "west-lancashire", "2XH": "west-lancashire", "2XJ": "west-lancashire", "2XL": "west-lancashire", "2XN": "west-lancashire", "2XP": "west-lancashire", "2XQ": "west-lancashire", "2XR": "west-lancashire", "2XS": "west-lancashire", "2XU": "west-lancashire", "2XW": "west-lancashire", "2XY": "west-lancashire", "2XZ": "west-lancashire", "2YA": "west-lancashire", "2YB": "west-lancashire", "2YD": "west-lancashire", "2YE": "west-lancashire", "2YF": "west-lancashire", "2YG": "west-lancashire", "2YH": "west-lancashire", "2YL": "west-lancashire", "2YN": "west-lancashire", "2YP": "west-lancashire", "2YQ": "west-lancashire", "2YR": "west-lancashire", "2YS": "west-lancashire", "2YT": "west-lancashire", "2YU": "west-lancashire", "2YW": "west-lancashire", "2YX": "west-lancashire", "2YY": "west-lancashire", "2YZ": "west-lancashire", "2ZA": "west-lancashire", "2ZB": "west-lancashire", "2ZX": "west-lancashire", "3AA": "west-lancashire", "3AD": "west-lancashire", "3AE": "west-lancashire", "3AF": "west-lancashire", "3AG": "west-lancashire", "3AH": "west-lancashire", "3AJ": "west-lancashire", "3AL": "west-lancashire", "3AN": "west-lancashire", "3AP": "west-lancashire", "3AQ": "west-lancashire", "3AR": "west-lancashire", "3AS": "west-lancashire", "3AT": "west-lancashire", "3AU": "west-lancashire", "3AW": "west-lancashire", "3AX": "west-lancashire", "3AY": "west-lancashire", "3AZ": "west-lancashire", "3BA": "west-lancashire", "3BB": "west-lancashire", "3BD": "west-lancashire", "3BE": "west-lancashire", "3BF": "west-lancashire", "3BG": "west-lancashire", "3BH": "west-lancashire", "3BJ": "west-lancashire", "3BL": "west-lancashire", "3BN": "west-lancashire", "3BP": "west-lancashire", "3BQ": "west-lancashire", "3BR": "west-lancashire", "3BS": "west-lancashire", "3BT": "west-lancashire", "3BU": "west-lancashire", "3BW": "west-lancashire", "3BX": "west-lancashire", "3BY": "west-lancashire", "3BZ": "west-lancashire", "3LA": "west-lancashire", "3LB": "west-lancashire", "3LD": "west-lancashire", "3LE": "west-lancashire", "3LF": "west-lancashire", "3LG": "west-lancashire", "3LH": "west-lancashire", "3LJ": "west-lancashire", "3LL": "west-lancashire", "3LN": "west-lancashire", "3LP": "west-lancashire", "3LQ": "west-lancashire", "3LR": "west-lancashire", "3LS": "west-lancashire", "3LT": "west-lancashire", "3LU": "west-lancashire", "3LW": "west-lancashire", "3LY": "west-lancashire", "3NA": "west-lancashire", "3NB": "west-lancashire", "3ND": "west-lancashire", "3NE": "west-lancashire", "3NF": "west-lancashire", "3NG": "west-lancashire", "3NH": "west-lancashire", "3NJ": "west-lancashire", "3NL": "west-lancashire", "3NN": "west-lancashire", "3NP": "west-lancashire", "3NQ": "west-lancashire", "3NR": "west-lancashire", "3NS": "west-lancashire", "3NT": "west-lancashire", "3NU": "west-lancashire", "3NW": "west-lancashire", "3NX": "west-lancashire", "3NY": "west-lancashire", "3NZ": "west-lancashire", "3PA": "west-lancashire", "3PB": "west-lancashire", "3PD": "west-lancashire", "3PF": "west-lancashire", "3PH": "west-lancashire", "3PJ": "west-lancashire", "3PL": "west-lancashire", "3PN": "west-lancashire", "3PP": "west-lancashire", "3PR": "west-lancashire", "3PS": "west-lancashire", "3PT": "west-lancashire", "3PU": "west-lancashire", "3PW": "west-lancashire", "3PX": "west-lancashire", "3PY": "west-lancashire", "3PZ": "west-lancashire", "3QA": "west-lancashire", "3QB": "west-lancashire", "3QG": "west-lancashire", "3QH": "west-lancashire", "3QL": "west-lancashire", "3QN": "west-lancashire", "3QQ": "west-lancashire", "3QR": "west-lancashire", "3QS": "west-lancashire", "3QT": "west-lancashire", "3QU": "west-lancashire", "3QW": "west-lancashire", "3QX": "west-lancashire", "3QY": "west-lancashire", "3QZ": "west-lancashire", "3RB": "west-lancashire", "3RD": "west-lancashire", "3RE": "west-lancashire", "3RF": "west-lancashire", "3RG": "west-lancashire", "3RH": "west-lancashire", "3RJ": "west-lancashire", "3RN": "west-lancashire", "3RP": "west-lancashire", "3RQ": "west-lancashire", "3RW": "west-lancashire", "3RX": "west-lancashire", "3WF": "west-lancashire", "3WG": "west-lancashire", "3WH": "west-lancashire", "3WJ": "west-lancashire", "3WL": "west-lancashire", "3WN": "west-lancashire", "3WP": "west-lancashire", "3WQ": "west-lancashire", "3WR": "west-lancashire", "3WS": "west-lancashire", "3WT": "west-lancashire", "3WU": "west-lancashire", "3WW": "west-lancashire", "3WX": "west-lancashire", "3WY": "west-lancashire", "3WZ": "west-lancashire", "3YQ": "west-lancashire", "3YR": "west-lancashire", "3YS": "west-lancashire", "3YT": "west-lancashire", "3YU": "west-lancashire", "3YW": "west-lancashire", "3YX": "west-lancashire", "4AA": "west-lancashire", "4AB": "west-lancashire", "4AD": "west-lancashire", "4AE": "west-lancashire", "4AF": "west-lancashire", "4AG": "west-lancashire", "4AH": "west-lancashire", "4AJ": "west-lancashire", "4AL": "west-lancashire", "4AN": "west-lancashire", "4AP": "west-lancashire", "4AQ": "west-lancashire", "4AR": "west-lancashire", "4AS": "west-lancashire", "4AT": "west-lancashire", "4AU": "west-lancashire", "4AW": "west-lancashire", "4AX": "west-lancashire", "4AY": "west-lancashire", "4AZ": "west-lancashire", "4BH": "west-lancashire", "4GA": "west-lancashire", "4PL": "west-lancashire", "4PS": "west-lancashire", "4PT": "west-lancashire", "4PY": "west-lancashire", "4PZ": "west-lancashire", "4QA": "west-lancashire", "4QB": "west-lancashire", "4QD": "west-lancashire", "4QE": "west-lancashire", "4QF": "west-lancashire", "4QG": "west-lancashire", "4QH": "west-lancashire", "4QJ": "west-lancashire", "4QL": "west-lancashire", "4QN": "west-lancashire", "4QP": "west-lancashire", "4QQ": "west-lancashire", "4QR": "west-lancashire", "4QS": "west-lancashire", "4QT": "west-lancashire", "4QU": "west-lancashire", "4QW": "west-lancashire", "4QX": "west-lancashire", "4QY": "west-lancashire", "4QZ": "west-lancashire", "4RA": "west-lancashire", "4RB": "west-lancashire", "4RD": "west-lancashire", "4RE": "west-lancashire", "4RF": "west-lancashire", "4RG": "west-lancashire", "4RH": "west-lancashire", "4RJ": "west-lancashire", "4RL": "west-lancashire", "4RN": "west-lancashire", "4RP": "west-lancashire", "4RQ": "west-lancashire", "4RR": "west-lancashire", "4RS": "west-lancashire", "4RT": "west-lancashire", "4RU": "west-lancashire", "4RW": "west-lancashire", "4RX": "west-lancashire", "4RY": "west-lancashire", "4RZ": "west-lancashire", "4SA": "west-lancashire", "4SB": "west-lancashire", "4SD": "west-lancashire", "4SE": "west-lancashire", "4SF": "west-lancashire", "4SG": "west-lancashire", "4SH": "west-lancashire", "4SJ": "west-lancashire", "4SL": "west-lancashire", "4SN": "west-lancashire", "4SP": "west-lancashire", "4SQ": "west-lancashire", "4SR": "west-lancashire", "4SS": "west-lancashire", "4ST": "west-lancashire", "4SU": "west-lancashire", "4SW": "west-lancashire", "4SX": "west-lancashire", "4SY": "west-lancashire", "4SZ": "west-lancashire", "4TA": "west-lancashire", "4TB": "west-lancashire", "4TD": "west-lancashire", "4TE": "west-lancashire", "4TF": "west-lancashire", "4TG": "west-lancashire", "4TH": "west-lancashire", "4TJ": "west-lancashire", "4TL": "west-lancashire", "4TN": "west-lancashire", "4TP": "west-lancashire", "4TQ": "west-lancashire", "4TR": "west-lancashire", "4TS": "west-lancashire", "4TT": "west-lancashire", "4TU": "west-lancashire", "4TW": "west-lancashire", "4TX": "west-lancashire", "4TY": "west-lancashire", "4TZ": "west-lancashire", "4UA": "west-lancashire", "4UB": "west-lancashire", "4UD": "west-lancashire", "4UE": "west-lancashire", "4UF": "west-lancashire", "4UG": "west-lancashire", "4UH": "west-lancashire", "4UJ": "west-lancashire", "4UL": "west-lancashire", "4UN": "west-lancashire", "4UP": "west-lancashire", "4UQ": "west-lancashire", "4UR": "west-lancashire", "4US": "west-lancashire", "4UT": "west-lancashire", "4UW": "west-lancashire", "4UX": "west-lancashire", "4UY": "west-lancashire", "4UZ": "west-lancashire", "4WA": "west-lancashire", "4WB": "west-lancashire", "4WD": "west-lancashire", "4WE": "west-lancashire", "4WG": "west-lancashire", "4WH": "west-lancashire", "4WJ": "west-lancashire", "4WN": "west-lancashire", "4WP": "west-lancashire", "4WQ": "west-lancashire", "4WR": "west-lancashire", "4WS": "west-lancashire", "4WT": "west-lancashire", "4WU": "west-lancashire", "4WW": "west-lancashire", "4WX": "west-lancashire", "4WY": "west-lancashire", "4WZ": "west-lancashire", "4XA": "west-lancashire", "4XB": "west-lancashire", "4XD": "west-lancashire", "4XE": "west-lancashire", "4XF": "west-lancashire", "4XG": "west-lancashire", "4XH": "west-lancashire", "4XJ": "west-lancashire", "4XL": "west-lancashire", "4XN": "west-lancashire", "4XP": "west-lancashire", "4XQ": "west-lancashire", "4XR": "west-lancashire", "4XS": "west-lancashire", "4XT": "west-lancashire", "4XW": "west-lancashire", "4XX": "west-lancashire", "4XY": "west-lancashire", "4XZ": "west-lancashire", "4YA": "west-lancashire", "4YB": "west-lancashire", "4YD": "west-lancashire", "4YE": "west-lancashire", "4YF": "west-lancashire", "4YG": "west-lancashire", "4YH": "west-lancashire", "4YJ": "west-lancashire", "4YL": "west-lancashire", "4YN": "west-lancashire", "4YP": "west-lancashire", "4YQ": "west-lancashire", "4YR": "west-lancashire", "4YS": "west-lancashire", "4YT": "west-lancashire", "4YU": "west-lancashire", "4YW": "west-lancashire", "4YX": "west-lancashire", "4ZY": "west-lancashire", "5AA": "west-lancashire", "5AB": "west-lancashire", "5AD": "west-lancashire", "5AE": "west-lancashire", "5AF": "west-lancashire", "5AG": "west-lancashire", "5AH": "west-lancashire", "5AJ": "west-lancashire", "5AL": "west-lancashire", "5AN": "west-lancashire", "5AP": "west-lancashire", "5AQ": "west-lancashire", "5AR": "west-lancashire", "5AS": "west-lancashire", "5AT": "west-lancashire", "5AU": "west-lancashire", "5AW": "west-lancashire", "5AX": "west-lancashire", "5AY": "west-lancashire", "5AZ": "west-lancashire", "5BA": "west-lancashire", "5BB": "west-lancashire", "5BD": "west-lancashire", "5BE": "west-lancashire", "5BF": "west-lancashire", "5BG": "west-lancashire", "5BH": "west-lancashire", "5BJ": "west-lancashire", "5BL": "west-lancashire", "5BN": "west-lancashire", "5BP": "west-lancashire", "5BQ": "west-lancashire", "5BR": "west-lancashire", "5BS": "west-lancashire", "5BT": "west-lancashire", "5BU": "west-lancashire", "5BW": "west-lancashire", "5BX": "west-lancashire", "5BY": "west-lancashire", "5BZ": "west-lancashire", "5DA": "west-lancashire", "5DB": "west-lancashire", "5DD": "west-lancashire", "5DE": "west-lancashire", "5DF": "west-lancashire", "5DG": "west-lancashire", "5DH": "west-lancashire", "5DJ": "west-lancashire", "5DL": "west-lancashire", "5DN": "west-lancashire", "5DP": "west-lancashire", "5DQ": "west-lancashire", "5DR": "west-lancashire", "5DS": "west-lancashire", "5DT": "west-lancashire", "5DU": "west-lancashire", "5DW": "west-lancashire", "5DX": "west-lancashire", "5DY": "west-lancashire", "5DZ": "west-lancashire", "5EA": "west-lancashire", "5EB": "west-lancashire", "5ED": "west-lancashire", "5EE": "west-lancashire", "5EF": "west-lancashire", "5EG": "west-lancashire", "5EH": "west-lancashire", "5EJ": "west-lancashire", "5EL": "west-lancashire", "5EN": "west-lancashire", "5EP": "west-lancashire", "5EQ": "west-lancashire", "5ER": "west-lancashire", "5ES": "west-lancashire", "5ET": "west-lancashire", "5EU": "west-lancashire", "5EW": "west-lancashire", "5EX": "west-lancashire", "5EY": "west-lancashire", "5EZ": "west-lancashire", "5FA": "west-lancashire", "5FB": "west-lancashire", "5FD": "west-lancashire", "5HA": "west-lancashire", "5HB": "west-lancashire", "5HD": "west-lancashire", "5HE": "west-lancashire", "5HF": "west-lancashire", "5HG": "west-lancashire", "5HH": "west-lancashire", "5HJ": "west-lancashire", "5HL": "west-lancashire", "5HP": "west-lancashire", "5HS": "west-lancashire", "5HT": "west-lancashire", "5HU": "west-lancashire", "5HW": "west-lancashire", "5HX": "west-lancashire", "5HY": "west-lancashire", "5JA": "west-lancashire", "5JB": "west-lancashire", "5JD": "west-lancashire", "5JE": "west-lancashire", "5JF": "west-lancashire", "5JG": "west-lancashire", "5JH": "west-lancashire", "5JJ": "west-lancashire", "5JL": "west-lancashire", "5JN": "west-lancashire", "5JP": "west-lancashire", "5JQ": "west-lancashire", "5JR": "west-lancashire", "5JS": "west-lancashire", "5JT": "west-lancashire", "5JU": "west-lancashire", "5JW": "west-lancashire", "5JX": "west-lancashire", "5QA": "west-lancashire", "5QB": "west-lancashire", "5QD": "west-lancashire", "5QE": "west-lancashire", "5QF": "west-lancashire", "5QG": "west-lancashire", "5QH": "west-lancashire", "5QJ": "west-lancashire", "5QL": "west-lancashire", "5QP": "west-lancashire", "5QQ": "west-lancashire", "5QR": "west-lancashire", "5QS": "west-lancashire", "5QT": "west-lancashire", "5QW": "west-lancashire", "5QX": "west-lancashire", "5QY": "west-lancashire", "5QZ": "west-lancashire", "5RA": "west-lancashire", "5RB": "west-lancashire", "5RD": "west-lancashire", "5RE": "west-lancashire", "5RF": "west-lancashire", "5RJ": "west-lancashire", "5RL": "west-lancashire", "5WA": "west-lancashire", "5WB": "west-lancashire", "5WD": "west-lancashire", "5WE": "west-lancashire", "5WP": "west-lancashire", "5WQ": "west-lancashire", "5WR": "west-lancashire", "5WS": "west-lancashire", "5WT": "west-lancashire", "5WU": "west-lancashire", "5WW": "west-lancashire", "5WX": "west-lancashire", "5WY": "west-lancashire", "5WZ": "west-lancashire", "5YP": "west-lancashire", "5YQ": "west-lancashire", "5YR": "west-lancashire", "5YS": "west-lancashire", "5YT": "west-lancashire", "5YU": "west-lancashire", "5YW": "west-lancashire", "5YX": "west-lancashire", "5ZY": "west-lancashire", "6AA": "west-lancashire", "6AB": "west-lancashire", "6AD": "west-lancashire", "6RA": "west-lancashire", "6RB": "west-lancashire", "6RD": "west-lancashire", "6RE": "west-lancashire", "6RF": "west-lancashire", "6RG": "west-lancashire", "6RH": "west-lancashire", "6RJ": "west-lancashire", "6RL": "west-lancashire", "6RN": "west-lancashire", "6RP": "west-lancashire", "6RQ": "west-lancashire", "6RR": "west-lancashire", "6RS": "west-lancashire", "6RT": "west-lancashire", "6RU": "west-lancashire", "6RW": "west-lancashire", "6RX": "west-lancashire", "6RY": "west-lancashire", "6RZ": "west-lancashire", "6SA": "west-lancashire", "6SB": "west-lancashire", "6SD": "west-lancashire", "6SE": "west-lancashire", "6SF": "west-lancashire", "6SG": "west-lancashire", "6SH": "west-lancashire", "6SJ": "west-lancashire", "6SL": "west-lancashire", "6SN": "west-lancashire", "6SP": "west-lancashire", "6SQ": "west-lancashire", "6SR": "west-lancashire", "6SS": "west-lancashire", "6ST": "west-lancashire", "6SU": "west-lancashire", "6SW": "west-lancashire", "6SX": "west-lancashire", "6SY": "west-lancashire", "6SZ": "west-lancashire", "6TA": "west-lancashire", "6TB": "west-lancashire", "6TD": "west-lancashire", "6TE": "west-lancashire", "6TF": "west-lancashire", "6TG": "west-lancashire", "6TH": "west-lancashire", "6TJ": "west-lancashire", "6TL": "west-lancashire", "6TN": "west-lancashire", "6TP": "west-lancashire", "6TQ": "west-lancashire", "6TR": "west-lancashire", "6TS": "west-lancashire", "6TT": "west-lancashire", "6TU": "west-lancashire", "6TW": "west-lancashire", "6TX": "west-lancashire", "6TY": "west-lancashire", "6TZ": "west-lancashire", "6UA": "west-lancashire", "6UB": "west-lancashire", "6UD": "west-lancashire", "6UE": "west-lancashire", "6UF": "west-lancashire", "6UH": "west-lancashire", "6WA": "west-lancashire", "6WB": "west-lancashire", "6WT": "west-lancashire", "6WU": "west-lancashire", "6WW": "west-lancashire", "6WX": "west-lancashire", "6WY": "west-lancashire", "6WZ": "west-lancashire", "6YT": "west-lancashire", "6YU": "west-lancashire", "6YW": "west-lancashire", "6YX": "west-lancashire", "6ZR": "west-lancashire", "7AA": "west-lancashire", "7AB": "west-lancashire", "7AD": "west-lancashire", "7AE": "west-lancashire", "7AF": "west-lancashire", "7AG": "west-lancashire", "7GZ": "west-lancashire", "7HA": "west-lancashire", "7HB": "west-lancashire", "7HD": "west-lancashire", "7HE": "west-lancashire", "7HF": "west-lancashire", "7HG": "west-lancashire", "7HH": "west-lancashire", "7HJ": "west-lancashire", "7HL": "west-lancashire", "7HN": "west-lancashire", "7HP": "west-lancashire", "7HQ": "west-lancashire", "7HR": "west-lancashire", "7HS": "west-lancashire", "7HT": "west-lancashire", "7HU": "west-lancashire", "7HW": "west-lancashire", "7HX": "west-lancashire", "7HY": "west-lancashire", "7HZ": "west-lancashire", "7JA": "west-lancashire", "7JB": "west-lancashire", "7JD": "west-lancashire", "7JE": "west-lancashire", "7JF": "west-lancashire", "7JG": "west-lancashire", "7JH": "west-lancashire", "7JJ": "west-lancashire", "7JL": "west-lancashire", "7JN": "west-lancashire", "7JP": "west-lancashire", "7JQ": "west-lancashire", "7JR": "west-lancashire", "7JS": "west-lancashire", "7JT": "west-lancashire", "7JU": "west-lancashire", "7JW": "west-lancashire", "7JX": "west-lancashire", "7JY": "west-lancashire", "7JZ": "west-lancashire", "7LA": "west-lancashire", "7LB": "west-lancashire", "7LD": "west-lancashire", "7LE": "west-lancashire", "7LF": "west-lancashire", "7LG": "west-lancashire", "7LH": "west-lancashire", "7LJ": "west-lancashire", "7LL": "west-lancashire", "7LP": "west-lancashire", "7LQ": "west-lancashire", "7LS": "west-lancashire", "7WW": "west-lancashire", "7WX": "west-lancashire", "7WY": "west-lancashire", "7WZ": "west-lancashire", "7YW": "west-lancashire", "7YX": "west-lancashire", "7ZY": "west-lancashire", "8AA": "west-lancashire", "8AB": "west-lancashire", "8BB": "west-lancashire", "8RA": "west-lancashire", "8RB": "west-lancashire", "8RD": "west-lancashire", "8RE": "west-lancashire", "8RF": "west-lancashire", "8RG": "west-lancashire", "8RH": "west-lancashire", "8RJ": "west-lancashire", "8RL": "west-lancashire", "8RN": "west-lancashire", "8RP": "west-lancashire", "8RQ": "west-lancashire", "8RR": "west-lancashire", "8RS": "west-lancashire", "8RT": "west-lancashire", "8RU": "west-lancashire", "8RW": "west-lancashire", "8RX": "west-lancashire", "8RY": "west-lancashire", "8RZ": "west-lancashire", "8SA": "west-lancashire", "8SB": "west-lancashire", "8SD": "west-lancashire", "8SE": "west-lancashire", "8SF": "west-lancashire", "8SG": "west-lancashire", "8SH": "west-lancashire", "8SJ": "west-lancashire", "8SL": "west-lancashire", "8SN": "west-lancashire", "8SP": "west-lancashire", "8SQ": "west-lancashire", "8SR": "west-lancashire", "8SS": "west-lancashire", "8ST": "west-lancashire", "8SU": "west-lancashire", "8SW": "west-lancashire", "8SX": "west-lancashire", "8SY": "west-lancashire", "8SZ": "west-lancashire", "8TB": "west-lancashire", "8TD": "west-lancashire", "8TE": "west-lancashire", "8TF": "west-lancashire", "8TG": "west-lancashire", "8TH": "west-lancashire", "8TJ": "west-lancashire", "8TL": "west-lancashire", "8TN": "west-lancashire", "8TP": "west-lancashire", "8TQ": "west-lancashire", "8TR": "west-lancashire", "8TS": "west-lancashire", "8TW": "west-lancashire", "8WA": "west-lancashire", "8WT": "west-lancashire", "8WU": "west-lancashire", "8WW": "west-lancashire", "8WX": "west-lancashire", "8WY": "west-lancashire", "8WZ": "west-lancashire", "8YW": "west-lancashire", "8YX": "west-lancashire", "9AA": "west-lancashire", "9EA": "west-lancashire", "9EB": "west-lancashire", "9ED": "west-lancashire", "9EE": "west-lancashire", "9EF": "west-lancashire", "9EG": "west-lancashire", "9EH": "west-lancashire", "9EJ": "west-lancashire", "9EL": "west-lancashire", "9EN": "west-lancashire", "9EP": "west-lancashire", "9EQ": "west-lancashire", "9ER": "west-lancashire", "9ES": "west-lancashire", "9EW": "west-lancashire", "9YU": "west-lancashire"}